{"updated":1782298459,"count":99,"btc_usd":62411,"coins":[{"name":"Abelian","tag":"ABEL","algo":"Abelhash","type":"gpu","unit":"MH/s","mult":1000000.0,"nethash":91078136272471.0,"reward":64.0,"blocktime":271.0,"price":0.0847925465},{"name":"Aeternity","tag":"AE","algo":"CuckooCycle","type":"gpu","unit":"MH/s","mult":1000000.0,"nethash":3367.0,"reward":33.858,"blocktime":180.0,"price":0.0052180029},{"name":"Aleo","tag":"ALEO","algo":"zkSNARK","type":"asic","unit":"MH/s","mult":1000000.0,"nethash":2610375712869.0,"reward":52.79410547692306,"blocktime":25.6,"price":0.027658212},{"name":"Alephium","tag":"ALPH","algo":"Blake3","type":"asic","unit":"GH/s","mult":1000000000.0,"nethash":5339605058249503.0,"reward":0.14331780723754928,"blocktime":0.5354,"price":0.0652250358},{"name":"Beam","tag":"BEAM","algo":"BeamHashIII","type":"gpu","unit":"MH/s","mult":1000000.0,"nethash":105388.0,"reward":25.0,"blocktime":60.0,"price":0.0097018495},{"name":"Bitcoin","tag":"BTC","algo":"SHA-256","type":"asic","unit":"TH/s","mult":1000000000000.0,"nethash":1.0625397498884645e+21,"reward":3.1460015533333334,"blocktime":505.0,"price":3899609662.03},{"name":"BitcoinCash","tag":"BCH","algo":"SHA-256","type":"asic","unit":"TH/s","mult":1000000000000.0,"nethash":3.496743188696926e+18,"reward":3.125,"blocktime":555.0,"price":191.8794697351},{"name":"Catcoin","tag":"CAT","algo":"Scrypt","type":"asic","unit":"GH/s","mult":1000000000.0,"nethash":2885968534212.0,"reward":25.0,"blocktime":605.0,"price":0.0469969856},{"name":"Conflux","tag":"CFX","algo":"Octopus","type":"gpu","unit":"MH/s","mult":1000000.0,"nethash":618281256048.0,"reward":0.40139541255427963,"blocktime":0.5064,"price":0.0455975939},{"name":"Dagger","tag":"XDAG","algo":"RandomX","type":"asic","unit":"kH/s","mult":1000.0,"nethash":2152239.0,"reward":64.0,"blocktime":64.0,"price":0.000821356},{"name":"Dash","tag":"DASH","algo":"X11","type":"asic","unit":"GH/s","mult":1000000000.0,"nethash":2829644142318334.0,"reward":0.4425562545486087,"blocktime":158.0,"price":35.4492575789},{"name":"Decred","tag":"DCR","algo":"Blake3DCR","type":"gpu","unit":"MH/s","mult":1000000.0,"nethash":26972173370956.0,"reward":0.05360599,"blocktime":294.0,"price":11.1571768711},{"name":"DGB-Qubit","tag":"DGB","algo":"Qubit","type":"asic","unit":"MH/s","mult":1000000.0,"nethash":42814573774948.0,"reward":259.3136889197038,"blocktime":75.0,"price":0.0025670496},{"name":"DGB-Scrypt","tag":"DGB","algo":"Scrypt","type":"asic","unit":"GH/s","mult":1000000000.0,"nethash":14197074419360.0,"reward":259.3136889197038,"blocktime":75.0,"price":0.0025670496},{"name":"DGB-SHA","tag":"DGB","algo":"SHA-256","type":"asic","unit":"TH/s","mult":1000000000000.0,"nethash":1.7513962230840626e+16,"reward":259.3136889197038,"blocktime":75.0,"price":0.0025670496},{"name":"DGB-Skein","tag":"DGB","algo":"Skein","type":"asic","unit":"MH/s","mult":1000000.0,"nethash":857655565291925.0,"reward":259.3136889197038,"blocktime":75.0,"price":0.0025670496},{"name":"Dingocoin","tag":"DINGO","algo":"Scrypt","type":"asic","unit":"GH/s","mult":1000000000.0,"nethash":1459846650004763.0,"reward":10000.0,"blocktime":62.0,"price":2.22444e-05},{"name":"Dogecoin","tag":"DOGE","algo":"Scrypt","type":"asic","unit":"GH/s","mult":1000000000.0,"nethash":1740394584723444.0,"reward":10000.0,"blocktime":63.0,"price":0.0785465252},{"name":"Dynexcoin","tag":"DNX","algo":"DynexSolve","type":"gpu","unit":"MH/s","mult":1000000.0,"nethash":4533446.0,"reward":9.540235136,"blocktime":129.0,"price":0.0100084971},{"name":"eCash","tag":"XEC","algo":"SHA-256","type":"asic","unit":"TH/s","mult":1000000000000.0,"nethash":3.812836184886435e+16,"reward":1812499.9999999998,"blocktime":625.0,"price":5.194e-06},{"name":"EPIC-ProgPow","tag":"EPIC","algo":"ProgPow","type":"gpu","unit":"MH/s","mult":1000000.0,"nethash":7527666607.0,"reward":0.9889,"blocktime":120.0,"price":0.169794852},{"name":"EPIC-RandomX","tag":"EPIC","algo":"RandomX","type":"asic","unit":"kH/s","mult":1000.0,"nethash":7116906.0,"reward":0.9889,"blocktime":120.0,"price":0.169794852},{"name":"Ergo","tag":"ERG","algo":"Autolykos","type":"gpu","unit":"MH/s","mult":1000000.0,"nethash":814614198254.0,"reward":3.0,"blocktime":119.0,"price":0.2222445706},{"name":"EthereumClassic","tag":"ETC","algo":"Etchash","type":"gpu","unit":"MH/s","mult":1000000.0,"nethash":191641325423004.0,"reward":1.98656,"blocktime":13.5838,"price":7.0129399116},{"name":"EthereumClassic","tag":"ETC","algo":"Etchash","type":"asic","unit":"MH/s","mult":1000000.0,"nethash":191641325423004.0,"reward":1.98656,"blocktime":13.5838,"price":7.0129399116},{"name":"EthereumPoW","tag":"ETHW","algo":"Ethash","type":"gpu","unit":"MH/s","mult":1000000.0,"nethash":1458402772645.0,"reward":2.000672656261347,"blocktime":13.0646,"price":0.2237428486},{"name":"EthereumPoW","tag":"ETHW","algo":"Ethash","type":"asic","unit":"MH/s","mult":1000000.0,"nethash":1458402772645.0,"reward":2.000672656261347,"blocktime":13.0646,"price":0.2237428486},{"name":"Etica","tag":"ETI","algo":"RandomX","type":"asic","unit":"kH/s","mult":1000.0,"nethash":3583296.0,"reward":31.96,"blocktime":435.0,"price":0.0176636988},{"name":"Evrmore","tag":"EVR","algo":"EvrProgPow","type":"gpu","unit":"MH/s","mult":1000000.0,"nethash":5058363872.0,"reward":1250.1,"blocktime":60.0,"price":3.41308e-05},{"name":"Firo","tag":"FIRO","algo":"FiroPow","type":"gpu","unit":"MH/s","mult":1000000.0,"nethash":11343220832.0,"reward":0.3125,"blocktime":152.0,"price":0.6840138515},{"name":"Fractal Bitcoin","tag":"FB","algo":"SHA-256","type":"asic","unit":"TH/s","mult":1000000000000.0,"nethash":6.002499857227648e+17,"reward":25.0001632,"blocktime":43.5,"price":0.3864558399},{"name":"Frencoin","tag":"FREN","algo":"KawPow","type":"gpu","unit":"MH/s","mult":1000000.0,"nethash":719549804.0,"reward":10000.0,"blocktime":30.0,"price":1.456e-07},{"name":"Grin-CT32","tag":"GRIN","algo":"Cuckatoo32","type":"gpu","unit":"MH/s","mult":1000000.0,"nethash":7188.0,"reward":60.0,"blocktime":61.0,"price":0.0246217019},{"name":"Grin-CT32","tag":"GRIN","algo":"Cuckatoo32","type":"asic","unit":"MH/s","mult":1000000.0,"nethash":7188.0,"reward":60.0,"blocktime":61.0,"price":0.0246217019},{"name":"Handshake","tag":"HNS","algo":"Handshake","type":"asic","unit":"GH/s","mult":1000000000.0,"nethash":1321598819607361.0,"reward":1000.0,"blocktime":683.0,"price":0.001929124},{"name":"IronFish","tag":"IRON","algo":"FishHash","type":"gpu","unit":"MH/s","mult":1000000.0,"nethash":392079531854.0,"reward":17.25,"blocktime":58.0,"price":0.0836838208},{"name":"Kadena","tag":"KDA","algo":"Kadena","type":"asic","unit":"MH/s","mult":1000000.0,"nethash":1.825863528670947e+16,"reward":0.917196,"blocktime":1.5021,"price":0.0070788641},{"name":"Karlsen","tag":"KLS","algo":"Karlsenhashv2","type":"gpu","unit":"MH/s","mult":1000000.0,"nethash":20074761241.0,"reward":21.82826757,"blocktime":1.0011,"price":6.56246e-05},{"name":"Kaspa","tag":"KAS","algo":"kHeavyHash","type":"asic","unit":"GH/s","mult":1000000000.0,"nethash":3.715005571973351e+17,"reward":2.544208056,"blocktime":0.1,"price":0.0282874887},{"name":"Kerrigan-KawPow","tag":"KRGN","algo":"KawPow","type":"gpu","unit":"MH/s","mult":1000000.0,"nethash":5503763887.0,"reward":5.0,"blocktime":480.0,"price":0.0388553429},{"name":"Keryx","tag":"KRX","algo":"KeryxHash","type":"gpu","unit":"MH/s","mult":1000000.0,"nethash":973878310075.0,"reward":4.75838766432,"blocktime":0.1002,"price":0.0005235782},{"name":"Larissa","tag":"LRS","algo":"Ethash","type":"gpu","unit":"MH/s","mult":1000000.0,"nethash":53812234516.0,"reward":1.23,"blocktime":13.0971,"price":0.0030744665},{"name":"Larissa","tag":"LRS","algo":"Ethash","type":"asic","unit":"MH/s","mult":1000000.0,"nethash":53812234516.0,"reward":1.23,"blocktime":13.0971,"price":0.0030744665},{"name":"Litecoin","tag":"LTC","algo":"Scrypt","type":"asic","unit":"GH/s","mult":1000000000.0,"nethash":2722040750276668.0,"reward":6.25,"blocktime":151.0,"price":41.8918529968},{"name":"MEWC-MeowPow","tag":"MEWC","algo":"MeowPow","type":"gpu","unit":"MH/s","mult":1000000.0,"nethash":3369059973.0,"reward":3000.0,"blocktime":131.0,"price":2.54108e-05},{"name":"MEWC-Scrypt","tag":"MEWC","algo":"Scrypt","type":"asic","unit":"GH/s","mult":1000000000.0,"nethash":297060537457055.0,"reward":3000.0,"blocktime":83.0,"price":2.54108e-05},{"name":"Monacoin","tag":"MONA","algo":"Lyra2REv2","type":"asic","unit":"MH/s","mult":1000000.0,"nethash":9074714486630.0,"reward":6.25,"blocktime":94.0,"price":0.0671355127},{"name":"Monero","tag":"XMR","algo":"RandomX","type":"asic","unit":"kH/s","mult":1000.0,"nethash":5732581558.0,"reward":0.66477088424,"blocktime":119.0,"price":321.9699545778},{"name":"MWC-CT31","tag":"MWC","algo":"Cuckatoo31","type":"asic","unit":"MH/s","mult":1000000.0,"nethash":4121.0,"reward":0.05,"blocktime":60.0,"price":3.1767199},{"name":"Neoxa","tag":"NEOX","algo":"KawPow","type":"gpu","unit":"MH/s","mult":1000000.0,"nethash":30217754641.0,"reward":500.0,"blocktime":16.9084,"price":6.965e-05},{"name":"Nervos","tag":"CKB","algo":"Eaglesong","type":"asic","unit":"GH/s","mult":1000000000.0,"nethash":6.65975278456617e+16,"reward":672.8073729275859,"blocktime":10.416,"price":0.00099186},{"name":"Neurai","tag":"XNA","algo":"KawPow","type":"gpu","unit":"MH/s","mult":1000000.0,"nethash":40193922551.0,"reward":3000.0,"blocktime":61.0,"price":3.32817e-05},{"name":"Nexa","tag":"NEXA","algo":"NexaPow","type":"gpu","unit":"MH/s","mult":1000000.0,"nethash":1175254011776.0,"reward":5000000.0,"blocktime":132.0,"price":4.396e-07},{"name":"Nicehash-Alephium","tag":"NICEHASH","algo":"Blake3","type":"asic","unit":"GH/s","mult":1000000000.0,"nethash":613279181923068.0,"reward":1.0,"blocktime":1.0,"price":0.2250030897},{"name":"Nicehash-Autolykos","tag":"NICEHASH","algo":"Autolykos","type":"gpu","unit":"MH/s","mult":1000000.0,"nethash":43875327890.0,"reward":1.0,"blocktime":1.0,"price":0.6053854473},{"name":"Nicehash-BeamV3","tag":"NICEHASH","algo":"BeamHashIII","type":"gpu","unit":"MH/s","mult":1000000.0,"nethash":7746.0,"reward":1.0,"blocktime":1.0,"price":3.1142904892},{"name":"Nicehash-Eaglesong","tag":"NICEHASH","algo":"Eaglesong","type":"asic","unit":"GH/s","mult":1000000000.0,"nethash":2163457719432205.0,"reward":1.0,"blocktime":1.0,"price":4.57644e-05},{"name":"Nicehash-Equihash","tag":"NICEHASH","algo":"Equihash","type":"asic","unit":"Sol/s","mult":1,"nethash":253095529.0,"reward":1.0,"blocktime":1.0,"price":26.6159745285},{"name":"Nicehash-Etchash","tag":"NICEHASH","algo":"Etchash","type":"gpu","unit":"MH/s","mult":1000000.0,"nethash":54586077157.0,"reward":1.0,"blocktime":1.0,"price":0.3224618905},{"name":"Nicehash-Etchash","tag":"NICEHASH","algo":"Etchash","type":"asic","unit":"MH/s","mult":1000000.0,"nethash":54586077157.0,"reward":1.0,"blocktime":1.0,"price":0.3224618905},{"name":"Nicehash-Ethash","tag":"NICEHASH","algo":"Ethash","type":"gpu","unit":"MH/s","mult":1000000.0,"nethash":10857752903.0,"reward":1.0,"blocktime":1.0,"price":1256.5048718131},{"name":"Nicehash-Ethash","tag":"NICEHASH","algo":"Ethash","type":"asic","unit":"MH/s","mult":1000000.0,"nethash":10857752903.0,"reward":1.0,"blocktime":1.0,"price":1256.5048718131},{"name":"Nicehash-FishHash","tag":"NICEHASH","algo":"FishHash","type":"gpu","unit":"MH/s","mult":1000000.0,"nethash":62031183653.0,"reward":1.0,"blocktime":1.0,"price":4.3135082472},{"name":"Nicehash-KawPow","tag":"NICEHASH","algo":"KawPow","type":"gpu","unit":"MH/s","mult":1000000.0,"nethash":153048892059.0,"reward":1.0,"blocktime":1.0,"price":4.647667146},{"name":"Nicehash-kHeavyHash","tag":"NICEHASH","algo":"kHeavyHash","type":"asic","unit":"GH/s","mult":1000000000.0,"nethash":4.883582049836859e+16,"reward":1.0,"blocktime":1.0,"price":0.0001663978},{"name":"Nicehash-NeoScrypt","tag":"NICEHASH","algo":"NeoScrypt","type":"gpu","unit":"MH/s","mult":1000000.0,"nethash":427564367.0,"reward":1.0,"blocktime":1.0,"price":50.347406869},{"name":"Nicehash-NexaPow","tag":"NICEHASH","algo":"NexaPow","type":"gpu","unit":"MH/s","mult":1000000.0,"nethash":17340930457.0,"reward":1.0,"blocktime":1.0,"price":1.0672310526},{"name":"Nicehash-Octopus","tag":"NICEHASH","algo":"Octopus","type":"gpu","unit":"MH/s","mult":1000000.0,"nethash":175972863180.0,"reward":1.0,"blocktime":1.0,"price":4.7056919446},{"name":"Nicehash-RandomX","tag":"NICEHASH","algo":"RandomX","type":"asic","unit":"kH/s","mult":1000.0,"nethash":122573865.0,"reward":1.0,"blocktime":1.0,"price":23.3859256965},{"name":"Nicehash-Scrypt","tag":"NICEHASH","algo":"Scrypt","type":"asic","unit":"GH/s","mult":1000000000.0,"nethash":182182093845348.0,"reward":1.0,"blocktime":1.0,"price":500.8673381503},{"name":"Nicehash-SHA-AB","tag":"NICEHASH","algo":"SHA-256","type":"asic","unit":"TH/s","mult":1000000000000.0,"nethash":1.4582874914036263e+19,"reward":1.0,"blocktime":1.0,"price":31.7232259612},{"name":"Nicehash-X11","tag":"NICEHASH","algo":"X11","type":"asic","unit":"GH/s","mult":1000000000.0,"nethash":56029189933215.0,"reward":1.0,"blocktime":1.0,"price":2.7293826986},{"name":"Nicehash-Zhash","tag":"NICEHASH","algo":"Zhash","type":"gpu","unit":"MH/s","mult":1000000.0,"nethash":9208.0,"reward":1.0,"blocktime":1.0,"price":561.7104685804},{"name":"OctaSpace","tag":"OCTA","algo":"Ethash","type":"gpu","unit":"MH/s","mult":1000000.0,"nethash":1217463622163.0,"reward":1.1,"blocktime":13.0597,"price":0.0859412263},{"name":"OctaSpace","tag":"OCTA","algo":"Ethash","type":"asic","unit":"MH/s","mult":1000000.0,"nethash":1217463622163.0,"reward":1.1,"blocktime":13.0597,"price":0.0859412263},{"name":"Pearl","tag":"PRL","algo":"Pearl","type":"gpu","unit":"MH/s","mult":1000000.0,"nethash":2.806010262535638e+19,"reward":2578.2756248887877,"blocktime":203.0,"price":0.709184922},{"name":"Peercoin","tag":"PPC","algo":"SHA-256","type":"asic","unit":"TH/s","mult":1000000000000.0,"nethash":8274842843769774.0,"reward":37.23193897015117,"blocktime":2700.0,"price":0.2354294171},{"name":"Phoenixcoin","tag":"PXC","algo":"NeoScrypt","type":"gpu","unit":"MH/s","mult":1000000.0,"nethash":754816641.0,"reward":3.125,"blocktime":90.0,"price":0.0227438601},{"name":"Pirate","tag":"ARRR","algo":"Equihash","type":"asic","unit":"Sol/s","mult":1,"nethash":4699245.0,"reward":0.25,"blocktime":59.0,"price":0.2440205431},{"name":"Quai-KawPow","tag":"QUAI","algo":"KawPow","type":"gpu","unit":"MH/s","mult":1000000.0,"nethash":263278314102.0,"reward":7.209022708887976,"blocktime":4.367,"price":0.0110572917},{"name":"Quai-Scrypt","tag":"QUAI","algo":"Scrypt","type":"asic","unit":"GH/s","mult":1000000000.0,"nethash":11143697631948.0,"reward":7.209022708887976,"blocktime":1.287,"price":0.0110572917},{"name":"Quai-SHA","tag":"QUAI","algo":"SHA-256","type":"asic","unit":"TH/s","mult":1000000000000.0,"nethash":1.472106625987381e+17,"reward":7.209022708887976,"blocktime":1.299,"price":0.0110572917},{"name":"Quantum R L","tag":"QRL","algo":"RandomX","type":"asic","unit":"kH/s","mult":1000.0,"nethash":65518830.0,"reward":1.31973299,"blocktime":60.0,"price":0.96330286},{"name":"QuarkChain","tag":"QKC","algo":"Ethash","type":"gpu","unit":"MH/s","mult":1000000.0,"nethash":39736330836.0,"reward":1.32819568820224,"blocktime":9.9275,"price":0.0020876007},{"name":"QuarkChain","tag":"QKC","algo":"Ethash","type":"asic","unit":"MH/s","mult":1000000.0,"nethash":39736330836.0,"reward":1.32819568820224,"blocktime":9.9275,"price":0.0020876007},{"name":"Qubitcoin","tag":"QTC","algo":"Qhash","type":"gpu","unit":"MH/s","mult":1000000.0,"nethash":10885312014550.0,"reward":50.0,"blocktime":679.0,"price":0.5887233704},{"name":"Radiant","tag":"RXD","algo":"SHA512256d","type":"asic","unit":"MH/s","mult":1000000.0,"nethash":478165484485054.0,"reward":12500.0,"blocktime":293.0,"price":7.79105e-05},{"name":"Ravencoin","tag":"RVN","algo":"KawPow","type":"gpu","unit":"MH/s","mult":1000000.0,"nethash":1548688743594.0,"reward":1250.0,"blocktime":60.0,"price":0.0039334792},{"name":"Ryo","tag":"RYO","algo":"CryptoNightGPU","type":"gpu","unit":"MH/s","mult":1000000.0,"nethash":558408.0,"reward":30.985,"blocktime":246.0,"price":0.0040107803},{"name":"ScPrime","tag":"SCP","algo":"Sia","type":"asic","unit":"MH/s","mult":1000000.0,"nethash":4151865837681494.0,"reward":44.99999999999999,"blocktime":578.0,"price":0.0218329071},{"name":"Tari-Cuckaroo29","tag":"XTM","algo":"Cuckaroo29","type":"gpu","unit":"MH/s","mult":1000000.0,"nethash":17273.0,"reward":10805.782812,"blocktime":312.0,"price":0.0005004249},{"name":"Tari-Merged","tag":"XTM","algo":"MoneroRandomX","type":"asic","unit":"MH/s","mult":1000000.0,"nethash":4055740597.0,"reward":10805.782812,"blocktime":1326.0,"price":0.0005004249},{"name":"Tari-RandomX","tag":"XTM","algo":"TariRandomX","type":"asic","unit":"MH/s","mult":1000000.0,"nethash":34318655.0,"reward":10805.782812,"blocktime":530.4,"price":0.0005004249},{"name":"Tari-SHA3x","tag":"XTM","algo":"SHA3x","type":"gpu","unit":"MH/s","mult":1000000.0,"nethash":477108597094816.0,"reward":10805.782812,"blocktime":589.3333,"price":0.0005004249},{"name":"Vertcoin","tag":"VTC","algo":"Verthash","type":"gpu","unit":"MH/s","mult":1000000.0,"nethash":942180988.0,"reward":6.25,"blocktime":141.0,"price":0.0414845917},{"name":"Xelis","tag":"XEL","algo":"Xelishashv3","type":"gpu","unit":"MH/s","mult":1000000.0,"nethash":52184209.0,"reward":0.32426792,"blocktime":6.0035,"price":0.2776808568},{"name":"Zano","tag":"ZANO","algo":"ProgPowZ","type":"gpu","unit":"MH/s","mult":1000000.0,"nethash":404571514965.0,"reward":1.0,"blocktime":120.0,"price":9.5700010387},{"name":"Zcash","tag":"ZEC","algo":"Equihash","type":"asic","unit":"Sol/s","mult":1,"nethash":21847642214.0,"reward":1.25,"blocktime":74.0,"price":410.2759899194},{"name":"Zephyr","tag":"ZEPH","algo":"RandomX","type":"asic","unit":"kH/s","mult":1000.0,"nethash":41003031.0,"reward":4.242606398678,"blocktime":122.0,"price":0.3542928054}]}