{"updated":1784498216,"count":98,"btc_usd":64331,"coins":[{"name":"Abelian","tag":"ABEL","algo":"Abelhash","type":"gpu","unit":"MH/s","mult":1000000.0,"nethash":142696859329385.0,"reward":64.0,"blocktime":272.0,"price":0.0838291794},{"name":"Aeternity","tag":"AE","algo":"CuckooCycle","type":"gpu","unit":"MH/s","mult":1000000.0,"nethash":3811.0,"reward":33.858,"blocktime":177.0,"price":0.0058544508},{"name":"Aleo","tag":"ALEO","algo":"zkSNARK","type":"asic","unit":"MH/s","mult":1000000.0,"nethash":1574100873691.0,"reward":45.086555931250004,"blocktime":21.0,"price":0.0189285248},{"name":"Alephium","tag":"ALPH","algo":"Blake3","type":"asic","unit":"GH/s","mult":1000000000.0,"nethash":4604879660922564.0,"reward":0.14331780723754928,"blocktime":0.5304,"price":0.036587819},{"name":"Beam","tag":"BEAM","algo":"BeamHashIII","type":"gpu","unit":"MH/s","mult":1000000.0,"nethash":75506.0,"reward":25.0,"blocktime":59.0,"price":0.0085607192},{"name":"Bitcoin","tag":"BTC","algo":"SHA-256","type":"asic","unit":"TH/s","mult":1000000000000.0,"nethash":1.1124096544982894e+21,"reward":3.138138392857143,"blocktime":491.0,"price":4140986470.0},{"name":"BitcoinCash","tag":"BCH","algo":"SHA-256","type":"asic","unit":"TH/s","mult":1000000000000.0,"nethash":3.29013499794571e+18,"reward":3.125,"blocktime":569.0,"price":215.7691921703},{"name":"Catcoin","tag":"CAT","algo":"Scrypt","type":"asic","unit":"GH/s","mult":1000000000.0,"nethash":2124048264757.0,"reward":25.0,"blocktime":609.0,"price":0.0532107415},{"name":"Conflux","tag":"CFX","algo":"Octopus","type":"gpu","unit":"MH/s","mult":1000000.0,"nethash":619711481849.0,"reward":0.40187785089000805,"blocktime":0.4979,"price":0.0457222813},{"name":"Dagger","tag":"XDAG","algo":"RandomX","type":"asic","unit":"kH/s","mult":1000.0,"nethash":2104149.0,"reward":64.0,"blocktime":64.0,"price":0.0006586007},{"name":"Dash","tag":"DASH","algo":"X11","type":"asic","unit":"GH/s","mult":1000000000.0,"nethash":2031177316203038.0,"reward":0.4425562545486087,"blocktime":157.0,"price":33.9394245767},{"name":"Decred","tag":"DCR","algo":"Blake3DCR","type":"gpu","unit":"MH/s","mult":1000000.0,"nethash":3018509345809.0,"reward":0.05307523,"blocktime":502.0,"price":12.592366009},{"name":"DGB-Qubit","tag":"DGB","algo":"Qubit","type":"asic","unit":"MH/s","mult":1000000.0,"nethash":46830423351826.0,"reward":256.41974815135995,"blocktime":75.0,"price":0.0036577825},{"name":"DGB-Scrypt","tag":"DGB","algo":"Scrypt","type":"asic","unit":"GH/s","mult":1000000000.0,"nethash":16223166368386.0,"reward":256.41974815135995,"blocktime":75.0,"price":0.0036577825},{"name":"DGB-SHA","tag":"DGB","algo":"SHA-256","type":"asic","unit":"TH/s","mult":1000000000000.0,"nethash":4.094028907178156e+16,"reward":256.41974815135995,"blocktime":75.0,"price":0.0036577825},{"name":"DGB-Skein","tag":"DGB","algo":"Skein","type":"asic","unit":"MH/s","mult":1000000.0,"nethash":900977701195429.0,"reward":256.41974815135995,"blocktime":75.0,"price":0.0036577825},{"name":"Dingocoin","tag":"DINGO","algo":"Scrypt","type":"asic","unit":"GH/s","mult":1000000000.0,"nethash":2916524034828240.0,"reward":10000.0,"blocktime":62.0,"price":2.49948e-05},{"name":"Dogecoin","tag":"DOGE","algo":"Scrypt","type":"asic","unit":"GH/s","mult":1000000000.0,"nethash":3147693341140406.0,"reward":10000.0,"blocktime":63.0,"price":0.0719077067},{"name":"Dynexcoin","tag":"DNX","algo":"DynexSolve","type":"gpu","unit":"MH/s","mult":1000000.0,"nethash":3467043.0,"reward":8.917626734,"blocktime":118.0,"price":0.007858236},{"name":"eCash","tag":"XEC","algo":"SHA-256","type":"asic","unit":"TH/s","mult":1000000000000.0,"nethash":4.402725103652955e+16,"reward":1812499.9999999998,"blocktime":623.0,"price":8.315e-06},{"name":"EPIC-ProgPow","tag":"EPIC","algo":"ProgPow","type":"gpu","unit":"MH/s","mult":1000000.0,"nethash":10321855407.0,"reward":0.9889,"blocktime":120.0,"price":0.2686371415},{"name":"EPIC-RandomX","tag":"EPIC","algo":"RandomX","type":"asic","unit":"kH/s","mult":1000.0,"nethash":7318279.0,"reward":0.9889,"blocktime":120.0,"price":0.2686371415},{"name":"Ergo","tag":"ERG","algo":"Autolykos","type":"gpu","unit":"MH/s","mult":1000000.0,"nethash":520228612778.0,"reward":3.0082,"blocktime":120.0,"price":0.2226650117},{"name":"EthereumClassic","tag":"ETC","algo":"Etchash","type":"gpu","unit":"MH/s","mult":1000000.0,"nethash":164364456670702.0,"reward":1.98656,"blocktime":13.545,"price":6.9177062125},{"name":"EthereumClassic","tag":"ETC","algo":"Etchash","type":"asic","unit":"MH/s","mult":1000000.0,"nethash":164364456670702.0,"reward":1.98656,"blocktime":13.545,"price":6.9177062125},{"name":"EthereumPoW","tag":"ETHW","algo":"Ethash","type":"gpu","unit":"MH/s","mult":1000000.0,"nethash":1573550938031.0,"reward":2.000529162226918,"blocktime":13.0245,"price":0.2366565294},{"name":"EthereumPoW","tag":"ETHW","algo":"Ethash","type":"asic","unit":"MH/s","mult":1000000.0,"nethash":1571593441359.0,"reward":2.0005312335789314,"blocktime":13.028,"price":0.2366565294},{"name":"Etica","tag":"ETI","algo":"RandomX","type":"asic","unit":"kH/s","mult":1000.0,"nethash":2919706.0,"reward":31.96,"blocktime":542.0,"price":0.0163151091},{"name":"Evrmore","tag":"EVR","algo":"EvrProgPow","type":"gpu","unit":"MH/s","mult":1000000.0,"nethash":3184968908.0,"reward":1250.1,"blocktime":61.0,"price":2.6324e-05},{"name":"Firo","tag":"FIRO","algo":"FiroPow","type":"gpu","unit":"MH/s","mult":1000000.0,"nethash":6733343138.0,"reward":0.3125,"blocktime":156.0,"price":0.6076316296},{"name":"Fractal Bitcoin","tag":"FB","algo":"SHA-256","type":"asic","unit":"TH/s","mult":1000000000000.0,"nethash":7.21138169010131e+17,"reward":25.01111682,"blocktime":42.0,"price":0.3768715256},{"name":"Frencoin","tag":"FREN","algo":"KawPow","type":"gpu","unit":"MH/s","mult":1000000.0,"nethash":557836462.0,"reward":10000.0,"blocktime":30.0,"price":9.98e-08},{"name":"Grin-CT32","tag":"GRIN","algo":"Cuckatoo32","type":"gpu","unit":"MH/s","mult":1000000.0,"nethash":4754.0,"reward":60.0,"blocktime":58.0,"price":0.0161202273},{"name":"Grin-CT32","tag":"GRIN","algo":"Cuckatoo32","type":"asic","unit":"MH/s","mult":1000000.0,"nethash":4754.0,"reward":60.0,"blocktime":58.0,"price":0.0161202273},{"name":"Handshake","tag":"HNS","algo":"Handshake","type":"asic","unit":"GH/s","mult":1000000000.0,"nethash":980093001146191.0,"reward":1000.0,"blocktime":605.0,"price":0.0012163062},{"name":"IronFish","tag":"IRON","algo":"FishHash","type":"gpu","unit":"MH/s","mult":1000000.0,"nethash":300258759268.0,"reward":17.25,"blocktime":60.0,"price":0.0777428692},{"name":"Kadena","tag":"KDA","algo":"Kadena","type":"asic","unit":"MH/s","mult":1000000.0,"nethash":1.452344551665064e+16,"reward":0.9145505,"blocktime":1.5014,"price":0.004838067},{"name":"Karlsen","tag":"KLS","algo":"Karlsenhashv2","type":"gpu","unit":"MH/s","mult":1000000.0,"nethash":10106736581.0,"reward":21.22471818,"blocktime":0.9971,"price":4.01856e-05},{"name":"Kaspa","tag":"KAS","algo":"kHeavyHash","type":"asic","unit":"GH/s","mult":1000000000.0,"nethash":3.114914734256551e+17,"reward":2.458730736,"blocktime":0.1,"price":0.0279730416},{"name":"Kerrigan-KawPow","tag":"KRGN","algo":"KawPow","type":"gpu","unit":"MH/s","mult":1000000.0,"nethash":5161448210.0,"reward":5.0,"blocktime":480.0,"price":0.023485762},{"name":"Keryx","tag":"KRX","algo":"KeryxHash","type":"gpu","unit":"MH/s","mult":1000000.0,"nethash":4296734232.0,"reward":4.69016760606,"blocktime":0.0869,"price":0.000767095},{"name":"Larissa","tag":"LRS","algo":"Ethash","type":"gpu","unit":"MH/s","mult":1000000.0,"nethash":68800352478.0,"reward":1.23,"blocktime":12.8376,"price":0.0035208655},{"name":"Larissa","tag":"LRS","algo":"Ethash","type":"asic","unit":"MH/s","mult":1000000.0,"nethash":68800352478.0,"reward":1.23,"blocktime":12.8376,"price":0.0035208655},{"name":"Litecoin","tag":"LTC","algo":"Scrypt","type":"asic","unit":"GH/s","mult":1000000000.0,"nethash":2731141477765836.0,"reward":6.25,"blocktime":152.0,"price":47.6511120087},{"name":"MEWC-MeowPow","tag":"MEWC","algo":"MeowPow","type":"gpu","unit":"MH/s","mult":1000000.0,"nethash":2100789584.0,"reward":3000.0,"blocktime":168.0,"price":1.69897e-05},{"name":"MEWC-Scrypt","tag":"MEWC","algo":"Scrypt","type":"asic","unit":"GH/s","mult":1000000000.0,"nethash":54279026655841.0,"reward":3000.0,"blocktime":172.0,"price":1.69897e-05},{"name":"Monero","tag":"XMR","algo":"RandomX","type":"asic","unit":"kH/s","mult":1000.0,"nethash":6039085902.0,"reward":0.62400946,"blocktime":121.0,"price":334.1674144788},{"name":"MWC-CT31","tag":"MWC","algo":"Cuckatoo31","type":"asic","unit":"MH/s","mult":1000000.0,"nethash":5898.0,"reward":0.05,"blocktime":61.0,"price":9.3344281},{"name":"Neoxa","tag":"NEOX","algo":"KawPow","type":"gpu","unit":"MH/s","mult":1000000.0,"nethash":6742685853.0,"reward":500.0,"blocktime":58.0,"price":3.80869e-05},{"name":"Nervos","tag":"CKB","algo":"Eaglesong","type":"asic","unit":"GH/s","mult":1000000000.0,"nethash":9.242813102760056e+16,"reward":737.949090566,"blocktime":9.0736,"price":0.0008995547},{"name":"Neurai","tag":"XNA","algo":"KawPow","type":"gpu","unit":"MH/s","mult":1000000.0,"nethash":44296511187.0,"reward":3000.0,"blocktime":60.0,"price":2.95021e-05},{"name":"Nexa","tag":"NEXA","algo":"NexaPow","type":"gpu","unit":"MH/s","mult":1000000.0,"nethash":1470893653430.0,"reward":5000000.0,"blocktime":122.0,"price":4.098e-07},{"name":"Nicehash-Alephium","tag":"NICEHASH","algo":"Blake3","type":"asic","unit":"GH/s","mult":1000000000.0,"nethash":592803013529383.0,"reward":1.0,"blocktime":1.0,"price":0.1544547016},{"name":"Nicehash-Autolykos","tag":"NICEHASH","algo":"Autolykos","type":"gpu","unit":"MH/s","mult":1000000.0,"nethash":37280539825.0,"reward":1.0,"blocktime":1.0,"price":0.9731232154},{"name":"Nicehash-BeamV3","tag":"NICEHASH","algo":"BeamHashIII","type":"gpu","unit":"MH/s","mult":1000000.0,"nethash":6675.0,"reward":1.0,"blocktime":1.0,"price":3.3082355831},{"name":"Nicehash-Eaglesong","tag":"NICEHASH","algo":"Eaglesong","type":"asic","unit":"GH/s","mult":1000000000.0,"nethash":2057112954793710.0,"reward":1.0,"blocktime":1.0,"price":4.20041e-05},{"name":"Nicehash-Equihash","tag":"NICEHASH","algo":"Equihash","type":"asic","unit":"Sol/s","mult":1,"nethash":287374327.0,"reward":1.0,"blocktime":1.0,"price":33.685684773},{"name":"Nicehash-Etchash","tag":"NICEHASH","algo":"Etchash","type":"gpu","unit":"MH/s","mult":1000000.0,"nethash":47756654014.0,"reward":1.0,"blocktime":1.0,"price":0.5144990788},{"name":"Nicehash-Etchash","tag":"NICEHASH","algo":"Etchash","type":"asic","unit":"MH/s","mult":1000000.0,"nethash":47756654014.0,"reward":1.0,"blocktime":1.0,"price":0.5144990788},{"name":"Nicehash-Ethash","tag":"NICEHASH","algo":"Ethash","type":"gpu","unit":"MH/s","mult":1000000.0,"nethash":11503679358.0,"reward":1.0,"blocktime":1.0,"price":1929.9293883395},{"name":"Nicehash-Ethash","tag":"NICEHASH","algo":"Ethash","type":"asic","unit":"MH/s","mult":1000000.0,"nethash":11503679358.0,"reward":1.0,"blocktime":1.0,"price":1929.9293883395},{"name":"Nicehash-FishHash","tag":"NICEHASH","algo":"FishHash","type":"gpu","unit":"MH/s","mult":1000000.0,"nethash":24121833772.0,"reward":1.0,"blocktime":1.0,"price":4.639546482},{"name":"Nicehash-KawPow","tag":"NICEHASH","algo":"KawPow","type":"gpu","unit":"MH/s","mult":1000000.0,"nethash":146719360726.0,"reward":1.0,"blocktime":1.0,"price":8.4557119475},{"name":"Nicehash-kHeavyHash","tag":"NICEHASH","algo":"kHeavyHash","type":"asic","unit":"GH/s","mult":1000000000.0,"nethash":4.340734101002299e+16,"reward":1.0,"blocktime":1.0,"price":0.0001856331},{"name":"Nicehash-NeoScrypt","tag":"NICEHASH","algo":"NeoScrypt","type":"gpu","unit":"MH/s","mult":1000000.0,"nethash":213168883.0,"reward":1.0,"blocktime":1.0,"price":57.882577206},{"name":"Nicehash-NexaPow","tag":"NICEHASH","algo":"NexaPow","type":"gpu","unit":"MH/s","mult":1000000.0,"nethash":9198388292.0,"reward":1.0,"blocktime":1.0,"price":0.8877703526},{"name":"Nicehash-Octopus","tag":"NICEHASH","algo":"Octopus","type":"gpu","unit":"MH/s","mult":1000000.0,"nethash":132864365909.0,"reward":1.0,"blocktime":1.0,"price":4.9059159211},{"name":"Nicehash-RandomX","tag":"NICEHASH","algo":"RandomX","type":"asic","unit":"kH/s","mult":1000.0,"nethash":106889082.0,"reward":1.0,"blocktime":1.0,"price":23.995497493},{"name":"Nicehash-Scrypt","tag":"NICEHASH","algo":"Scrypt","type":"asic","unit":"GH/s","mult":1000000000.0,"nethash":221201535075654.0,"reward":1.0,"blocktime":1.0,"price":458.5206652549},{"name":"Nicehash-SHA-AB","tag":"NICEHASH","algo":"SHA-256","type":"asic","unit":"TH/s","mult":1000000000000.0,"nethash":1.1821559035139856e+19,"reward":1.0,"blocktime":1.0,"price":32.3311595323},{"name":"Nicehash-X11","tag":"NICEHASH","algo":"X11","type":"asic","unit":"GH/s","mult":1000000000.0,"nethash":25436253179818.0,"reward":1.0,"blocktime":1.0,"price":3.4383167877},{"name":"Nicehash-Zhash","tag":"NICEHASH","algo":"Zhash","type":"gpu","unit":"MH/s","mult":1000000.0,"nethash":6580.0,"reward":1.0,"blocktime":1.0,"price":578.9961848902},{"name":"OctaSpace","tag":"OCTA","algo":"Ethash","type":"gpu","unit":"MH/s","mult":1000000.0,"nethash":1232634953327.0,"reward":1.1,"blocktime":12.8329,"price":0.0853982282},{"name":"OctaSpace","tag":"OCTA","algo":"Ethash","type":"asic","unit":"MH/s","mult":1000000.0,"nethash":1232634953327.0,"reward":1.1,"blocktime":12.8329,"price":0.0853982282},{"name":"Pearl","tag":"PRL","algo":"Pearl","type":"gpu","unit":"MH/s","mult":1000000.0,"nethash":5.479006058358444e+19,"reward":2495.3186190797637,"blocktime":145.0,"price":0.3198061209},{"name":"Peercoin","tag":"PPC","algo":"SHA-256","type":"asic","unit":"TH/s","mult":1000000000000.0,"nethash":8222114577522014.0,"reward":37.29148788480071,"blocktime":2700.0,"price":0.2436522883},{"name":"Phoenixcoin","tag":"PXC","algo":"NeoScrypt","type":"gpu","unit":"MH/s","mult":1000000.0,"nethash":884620097.0,"reward":3.125,"blocktime":90.0,"price":0.0226462709},{"name":"Pirate","tag":"ARRR","algo":"Equihash","type":"asic","unit":"Sol/s","mult":1,"nethash":3010671.0,"reward":0.25,"blocktime":61.0,"price":0.2127110461},{"name":"Quai-KawPow","tag":"QUAI","algo":"KawPow","type":"gpu","unit":"MH/s","mult":1000000.0,"nethash":283572981062.0,"reward":9.0588913466103,"blocktime":2.883,"price":0.017359476},{"name":"Quai-Scrypt","tag":"QUAI","algo":"Scrypt","type":"asic","unit":"GH/s","mult":1000000000.0,"nethash":19542567882729.0,"reward":9.0588913466103,"blocktime":1.399,"price":0.017359476},{"name":"Quai-SHA","tag":"QUAI","algo":"SHA-256","type":"asic","unit":"TH/s","mult":1000000000000.0,"nethash":2.715083924601323e+17,"reward":9.0588913466103,"blocktime":1.329,"price":0.017359476},{"name":"Quantum R L","tag":"QRL","algo":"RandomX","type":"asic","unit":"kH/s","mult":1000.0,"nethash":77254897.0,"reward":1.311727582,"blocktime":60.0,"price":0.9856124827},{"name":"QuarkChain","tag":"QKC","algo":"Ethash","type":"gpu","unit":"MH/s","mult":1000000.0,"nethash":36725585081.0,"reward":1.32819568820224,"blocktime":9.7913,"price":0.0019058446},{"name":"QuarkChain","tag":"QKC","algo":"Ethash","type":"asic","unit":"MH/s","mult":1000000.0,"nethash":36725585081.0,"reward":1.32819568820224,"blocktime":9.7913,"price":0.0019058446},{"name":"Qubitcoin","tag":"QTC","algo":"Qhash","type":"gpu","unit":"MH/s","mult":1000000.0,"nethash":11323582316059.0,"reward":50.0,"blocktime":521.0,"price":0.4219442007},{"name":"Radiant","tag":"RXD","algo":"SHA512256d","type":"asic","unit":"MH/s","mult":1000000.0,"nethash":396609596234745.0,"reward":12500.0,"blocktime":301.0,"price":7.29558e-05},{"name":"Ravencoin","tag":"RVN","algo":"KawPow","type":"gpu","unit":"MH/s","mult":1000000.0,"nethash":1491650218876.0,"reward":1250.0,"blocktime":60.0,"price":0.0037442391},{"name":"Ryo","tag":"RYO","algo":"CryptoNightGPU","type":"gpu","unit":"MH/s","mult":1000000.0,"nethash":235630.0,"reward":30.995,"blocktime":248.0,"price":0.0036831271},{"name":"ScPrime","tag":"SCP","algo":"Sia","type":"asic","unit":"MH/s","mult":1000000.0,"nethash":3552291491807515.0,"reward":45.0000162,"blocktime":417.0,"price":0.0156615054},{"name":"Tari-Cuckaroo29","tag":"XTM","algo":"Cuckaroo29","type":"gpu","unit":"MH/s","mult":1000000.0,"nethash":196695.0,"reward":10652.049042,"blocktime":467.0769,"price":0.0004147486},{"name":"Tari-Merged","tag":"XTM","algo":"MoneroRandomX","type":"asic","unit":"MH/s","mult":1000000.0,"nethash":2804567438.0,"reward":10652.049042,"blocktime":467.0769,"price":0.0004147486},{"name":"Tari-RandomX","tag":"XTM","algo":"TariRandomX","type":"asic","unit":"MH/s","mult":1000000.0,"nethash":29882296.0,"reward":10652.049042,"blocktime":674.6667,"price":0.0004147486},{"name":"Tari-SHA3x","tag":"XTM","algo":"SHA3x","type":"gpu","unit":"MH/s","mult":1000000.0,"nethash":282139847985720.0,"reward":10652.049042,"blocktime":1214.4,"price":0.0004147486},{"name":"Vertcoin","tag":"VTC","algo":"Verthash","type":"gpu","unit":"MH/s","mult":1000000.0,"nethash":718677668.0,"reward":6.25,"blocktime":156.0,"price":0.0441503653},{"name":"Xelis","tag":"XEL","algo":"Xelishashv3","type":"gpu","unit":"MH/s","mult":1000000.0,"nethash":68710436.0,"reward":0.32050944,"blocktime":5.7959,"price":0.2528467143},{"name":"Zano","tag":"ZANO","algo":"ProgPowZ","type":"gpu","unit":"MH/s","mult":1000000.0,"nethash":414123898856.0,"reward":1.0,"blocktime":120.0,"price":9.4662611776},{"name":"Zcash","tag":"ZEC","algo":"Equihash","type":"asic","unit":"Sol/s","mult":1,"nethash":19772511123.0,"reward":1.25,"blocktime":75.0,"price":545.4407820707},{"name":"Zephyr","tag":"ZEPH","algo":"RandomX","type":"asic","unit":"kH/s","mult":1000.0,"nethash":56696634.0,"reward":4.169261556301,"blocktime":121.0,"price":0.4467291751}]}