{"updated":1780655663,"count":97,"btc_usd":62565,"coins":[{"name":"Abelian","tag":"ABEL","algo":"Abelhash","type":"gpu","unit":"MH/s","mult":1000000.0,"nethash":38179304483985.0,"reward":64.0,"blocktime":230.0,"price":0.0656681342},{"name":"Aeternity","tag":"AE","algo":"CuckooCycle","type":"gpu","unit":"MH/s","mult":1000000.0,"nethash":4133.0,"reward":34.749,"blocktime":183.0,"price":0.0051195157},{"name":"Alephium","tag":"ALPH","algo":"Blake3","type":"asic","unit":"GH/s","mult":1000000000.0,"nethash":5898160586950909.0,"reward":0.14331780723754928,"blocktime":0.5298,"price":0.0341850825},{"name":"Beam","tag":"BEAM","algo":"BeamHashIII","type":"gpu","unit":"MH/s","mult":1000000.0,"nethash":128112.0,"reward":25.0,"blocktime":60.0,"price":0.016082196},{"name":"Bitcoin","tag":"BTC","algo":"SHA-256","type":"asic","unit":"TH/s","mult":1000000000000.0,"nethash":9.564242211083621e+20,"reward":3.1615529639999997,"blocktime":624.0,"price":3914942310.0},{"name":"BitcoinCash","tag":"BCH","algo":"SHA-256","type":"asic","unit":"TH/s","mult":1000000000000.0,"nethash":4.245633447357627e+18,"reward":3.125,"blocktime":579.0,"price":232.0666171253},{"name":"Catcoin","tag":"CAT","algo":"Scrypt","type":"asic","unit":"GH/s","mult":1000000000.0,"nethash":3761113724884.0,"reward":25.0,"blocktime":627.0,"price":0.0568688194},{"name":"Conflux","tag":"CFX","algo":"Octopus","type":"gpu","unit":"MH/s","mult":1000000.0,"nethash":690179780095.0,"reward":0.40174612554623984,"blocktime":0.505,"price":0.0460876357},{"name":"Cortex","tag":"CTXC","algo":"Cortex","type":"gpu","unit":"MH/s","mult":1000000.0,"nethash":388.0,"reward":3.5,"blocktime":18.0769,"price":0.0009560361},{"name":"Dagger","tag":"XDAG","algo":"RandomX","type":"asic","unit":"kH/s","mult":1000.0,"nethash":2367775.0,"reward":64.0,"blocktime":64.0,"price":0.0010195533},{"name":"Dash","tag":"DASH","algo":"X11","type":"asic","unit":"GH/s","mult":1000000000.0,"nethash":1795523433550747.0,"reward":0.4425562545486087,"blocktime":158.0,"price":31.9853988877},{"name":"Decred","tag":"DCR","algo":"Blake3DCR","type":"gpu","unit":"MH/s","mult":1000000.0,"nethash":18606541067535.0,"reward":0.05414205,"blocktime":308.0,"price":12.6238741977},{"name":"DGB-Qubit","tag":"DGB","algo":"Qubit","type":"asic","unit":"MH/s","mult":1000000.0,"nethash":79563999371136.0,"reward":262.24029056238,"blocktime":75.0,"price":0.0026896131},{"name":"DGB-Scrypt","tag":"DGB","algo":"Scrypt","type":"asic","unit":"GH/s","mult":1000000000.0,"nethash":14385135632528.0,"reward":262.24029056238,"blocktime":75.0,"price":0.0026896131},{"name":"DGB-SHA","tag":"DGB","algo":"SHA-256","type":"asic","unit":"TH/s","mult":1000000000000.0,"nethash":2.2674510001192052e+16,"reward":262.24029056238,"blocktime":75.0,"price":0.0026896131},{"name":"DGB-Skein","tag":"DGB","algo":"Skein","type":"asic","unit":"MH/s","mult":1000000.0,"nethash":1844610232329682.0,"reward":262.24029056238,"blocktime":75.0,"price":0.0026896131},{"name":"Dingocoin","tag":"DINGO","algo":"Scrypt","type":"asic","unit":"GH/s","mult":1000000000.0,"nethash":1268544980782448.0,"reward":10000.0,"blocktime":63.0,"price":2.0817e-05},{"name":"Dogecoin","tag":"DOGE","algo":"Scrypt","type":"asic","unit":"GH/s","mult":1000000000.0,"nethash":2238325799374523.0,"reward":10000.0,"blocktime":63.0,"price":0.0848477946},{"name":"Dynexcoin","tag":"DNX","algo":"DynexSolve","type":"gpu","unit":"MH/s","mult":1000000.0,"nethash":5591825.0,"reward":10.045965371,"blocktime":127.0,"price":0.0144929672},{"name":"eCash","tag":"XEC","algo":"SHA-256","type":"asic","unit":"TH/s","mult":1000000000000.0,"nethash":4.320364811361619e+16,"reward":1812499.9999999998,"blocktime":706.0,"price":5.7392e-06},{"name":"EPIC-ProgPow","tag":"EPIC","algo":"ProgPow","type":"gpu","unit":"MH/s","mult":1000000.0,"nethash":8457793435.0,"reward":0.9889,"blocktime":120.0,"price":0.2098081895},{"name":"EPIC-RandomX","tag":"EPIC","algo":"RandomX","type":"asic","unit":"kH/s","mult":1000.0,"nethash":7407026.0,"reward":0.9889,"blocktime":120.0,"price":0.2098798087},{"name":"Ergo","tag":"ERG","algo":"Autolykos","type":"gpu","unit":"MH/s","mult":1000000.0,"nethash":836751131664.0,"reward":3.0015,"blocktime":126.0,"price":0.2133964482},{"name":"EthereumClassic","tag":"ETC","algo":"Etchash","type":"gpu","unit":"MH/s","mult":1000000.0,"nethash":192887474104112.0,"reward":1.98656,"blocktime":13.4819,"price":7.0165951598},{"name":"EthereumClassic","tag":"ETC","algo":"Etchash","type":"asic","unit":"MH/s","mult":1000000.0,"nethash":193358319697923.0,"reward":1.98656,"blocktime":13.4688,"price":7.0189903155},{"name":"EthereumPoW","tag":"ETHW","algo":"Ethash","type":"gpu","unit":"MH/s","mult":1000000.0,"nethash":1070645729133.0,"reward":2.00089142502291,"blocktime":13.0738,"price":0.2327870388},{"name":"EthereumPoW","tag":"ETHW","algo":"Ethash","type":"asic","unit":"MH/s","mult":1000000.0,"nethash":1072028496403.0,"reward":2.000884360994367,"blocktime":13.0697,"price":0.2328665021},{"name":"Etica","tag":"ETI","algo":"RandomX","type":"asic","unit":"kH/s","mult":1000.0,"nethash":744894.0,"reward":31.96,"blocktime":3469.0,"price":0.0252603663},{"name":"Evrmore","tag":"EVR","algo":"EvrProgPow","type":"gpu","unit":"MH/s","mult":1000000.0,"nethash":6028217927.0,"reward":1250.1,"blocktime":60.0,"price":4.48482e-05},{"name":"Firo","tag":"FIRO","algo":"FiroPow","type":"gpu","unit":"MH/s","mult":1000000.0,"nethash":10366877341.0,"reward":0.3125,"blocktime":163.0,"price":0.7378419583},{"name":"Fractal Bitcoin","tag":"FB","algo":"SHA-256","type":"asic","unit":"TH/s","mult":1000000000000.0,"nethash":6.705256030453597e+17,"reward":25.00007085,"blocktime":45.0,"price":0.4021421517},{"name":"Frencoin","tag":"FREN","algo":"KawPow","type":"gpu","unit":"MH/s","mult":1000000.0,"nethash":656609415.0,"reward":10000.0,"blocktime":30.0,"price":1.218e-07},{"name":"Grin-CT32","tag":"GRIN","algo":"Cuckatoo32","type":"gpu","unit":"MH/s","mult":1000000.0,"nethash":8342.0,"reward":60.0,"blocktime":60.0,"price":0.0270968511},{"name":"Grin-CT32","tag":"GRIN","algo":"Cuckatoo32","type":"asic","unit":"MH/s","mult":1000000.0,"nethash":8380.0,"reward":60.0,"blocktime":60.0,"price":0.0271061008},{"name":"Handshake","tag":"HNS","algo":"Handshake","type":"asic","unit":"GH/s","mult":1000000000.0,"nethash":1693002366936960.0,"reward":1000.0,"blocktime":549.0,"price":0.0028565891},{"name":"IronFish","tag":"IRON","algo":"FishHash","type":"gpu","unit":"MH/s","mult":1000000.0,"nethash":368409276840.0,"reward":17.25000101,"blocktime":60.0,"price":0.1011609111},{"name":"Kadena","tag":"KDA","algo":"Kadena","type":"asic","unit":"MH/s","mult":1000000.0,"nethash":2.2149030016340652e+16,"reward":0.917196,"blocktime":1.5047,"price":0.0065930997},{"name":"Karlsen","tag":"KLS","algo":"Karlsenhashv2","type":"gpu","unit":"MH/s","mult":1000000.0,"nethash":21870101863.0,"reward":21.82826757,"blocktime":0.998,"price":0.0001019705},{"name":"Kaspa","tag":"KAS","algo":"kHeavyHash","type":"asic","unit":"GH/s","mult":1000000000.0,"nethash":3.941217228233722e+17,"reward":2.5470796458000002,"blocktime":0.1,"price":0.0295357513},{"name":"Larissa","tag":"LRS","algo":"Ethash","type":"gpu","unit":"MH/s","mult":1000000.0,"nethash":60113587264.0,"reward":1.23,"blocktime":12.6348,"price":0.0030285304},{"name":"Larissa","tag":"LRS","algo":"Ethash","type":"asic","unit":"MH/s","mult":1000000.0,"nethash":60223438320.0,"reward":1.23,"blocktime":12.6303,"price":0.0030295642},{"name":"Litecoin","tag":"LTC","algo":"Scrypt","type":"asic","unit":"GH/s","mult":1000000000.0,"nethash":3075148399604764.0,"reward":6.25,"blocktime":137.0,"price":44.4736024547},{"name":"MEWC-MeowPow","tag":"MEWC","algo":"MeowPow","type":"gpu","unit":"MH/s","mult":1000000.0,"nethash":5254676388.0,"reward":3000.0,"blocktime":112.0,"price":2.64372e-05},{"name":"MEWC-Scrypt","tag":"MEWC","algo":"Scrypt","type":"asic","unit":"GH/s","mult":1000000000.0,"nethash":61605631563103.0,"reward":3000.0,"blocktime":104.0,"price":2.64462e-05},{"name":"Monacoin","tag":"MONA","algo":"Lyra2REv2","type":"asic","unit":"MH/s","mult":1000000.0,"nethash":13503172170551.0,"reward":6.25,"blocktime":94.0,"price":0.0692031465},{"name":"Monero","tag":"XMR","algo":"RandomX","type":"asic","unit":"kH/s","mult":1000.0,"nethash":5743155607.0,"reward":0.60141952,"blocktime":122.0,"price":333.3520471761},{"name":"MWC-CT31","tag":"MWC","algo":"Cuckatoo31","type":"asic","unit":"MH/s","mult":1000000.0,"nethash":3945.0,"reward":0.05,"blocktime":60.0,"price":2.590191},{"name":"Neoxa","tag":"NEOX","algo":"KawPow","type":"gpu","unit":"MH/s","mult":1000000.0,"nethash":27612930549.0,"reward":1125.0,"blocktime":60.0,"price":8.8607e-05},{"name":"Nervos","tag":"CKB","algo":"Eaglesong","type":"asic","unit":"GH/s","mult":1000000000.0,"nethash":8.622739674029715e+16,"reward":659.1232501416666,"blocktime":9.2638,"price":0.001077845},{"name":"Neurai","tag":"XNA","algo":"KawPow","type":"gpu","unit":"MH/s","mult":1000000.0,"nethash":54856731937.0,"reward":3000.0,"blocktime":60.0,"price":4.08402e-05},{"name":"Nexa","tag":"NEXA","algo":"NexaPow","type":"gpu","unit":"MH/s","mult":1000000.0,"nethash":1556091499085.0,"reward":5000000.0,"blocktime":148.0,"price":4.33e-07},{"name":"Nicehash-Alephium","tag":"NICEHASH","algo":"Blake3","type":"asic","unit":"GH/s","mult":1000000000.0,"nethash":642367824897122.0,"reward":1.0,"blocktime":1.0,"price":0.1076528507},{"name":"Nicehash-Autolykos","tag":"NICEHASH","algo":"Autolykos","type":"gpu","unit":"MH/s","mult":1000000.0,"nethash":38371729954.0,"reward":1.0,"blocktime":1.0,"price":0.5380605555},{"name":"Nicehash-BeamV3","tag":"NICEHASH","algo":"BeamHashIII","type":"gpu","unit":"MH/s","mult":1000000.0,"nethash":17818.0,"reward":1.0,"blocktime":1.0,"price":4.5046726729},{"name":"Nicehash-Eaglesong","tag":"NICEHASH","algo":"Eaglesong","type":"asic","unit":"GH/s","mult":1000000000.0,"nethash":2504658167763654.0,"reward":1.0,"blocktime":1.0,"price":6.61641e-05},{"name":"Nicehash-Equihash","tag":"NICEHASH","algo":"Equihash","type":"asic","unit":"Sol/s","mult":1,"nethash":257545312.0,"reward":1.0,"blocktime":1.0,"price":21.7083514966},{"name":"Nicehash-Etchash","tag":"NICEHASH","algo":"Etchash","type":"gpu","unit":"MH/s","mult":1000000.0,"nethash":61905568655.0,"reward":1.0,"blocktime":1.0,"price":0.4129285241},{"name":"Nicehash-Etchash","tag":"NICEHASH","algo":"Etchash","type":"asic","unit":"MH/s","mult":1000000.0,"nethash":60917521540.0,"reward":1.0,"blocktime":1.0,"price":0.4129284605},{"name":"Nicehash-Ethash","tag":"NICEHASH","algo":"Ethash","type":"gpu","unit":"MH/s","mult":1000000.0,"nethash":17189791542.0,"reward":1.0,"blocktime":1.0,"price":2508.8592964279},{"name":"Nicehash-Ethash","tag":"NICEHASH","algo":"Ethash","type":"asic","unit":"MH/s","mult":1000000.0,"nethash":17231293453.0,"reward":1.0,"blocktime":1.0,"price":2508.8591571168},{"name":"Nicehash-FishHash","tag":"NICEHASH","algo":"FishHash","type":"gpu","unit":"MH/s","mult":1000000.0,"nethash":15675735845.0,"reward":1.0,"blocktime":1.0,"price":2.8842485862},{"name":"Nicehash-KawPow","tag":"NICEHASH","algo":"KawPow","type":"gpu","unit":"MH/s","mult":1000000.0,"nethash":258140017483.0,"reward":1.0,"blocktime":1.0,"price":11.0813381355},{"name":"Nicehash-kHeavyHash","tag":"NICEHASH","algo":"kHeavyHash","type":"asic","unit":"GH/s","mult":1000000000.0,"nethash":5.390638696164054e+16,"reward":1.0,"blocktime":1.0,"price":0.0001649602},{"name":"Nicehash-NeoScrypt","tag":"NICEHASH","algo":"NeoScrypt","type":"gpu","unit":"MH/s","mult":1000000.0,"nethash":208222587.0,"reward":1.0,"blocktime":1.0,"price":47.2822973144},{"name":"Nicehash-NexaPow","tag":"NICEHASH","algo":"NexaPow","type":"gpu","unit":"MH/s","mult":1000000.0,"nethash":11108747988.0,"reward":1.0,"blocktime":1.0,"price":0.7507768984},{"name":"Nicehash-Octopus","tag":"NICEHASH","algo":"Octopus","type":"gpu","unit":"MH/s","mult":1000000.0,"nethash":73159399178.0,"reward":1.0,"blocktime":1.0,"price":4.3244011667},{"name":"Nicehash-RandomX","tag":"NICEHASH","algo":"RandomX","type":"asic","unit":"kH/s","mult":1000.0,"nethash":139168839.0,"reward":1.0,"blocktime":1.0,"price":22.7686255926},{"name":"Nicehash-Scrypt","tag":"NICEHASH","algo":"Scrypt","type":"asic","unit":"GH/s","mult":1000000000.0,"nethash":182095121449571.0,"reward":1.0,"blocktime":1.0,"price":481.5699140834},{"name":"Nicehash-SHA-AB","tag":"NICEHASH","algo":"SHA-256","type":"asic","unit":"TH/s","mult":1000000000000.0,"nethash":1.549346406213626e+19,"reward":1.0,"blocktime":1.0,"price":28.7112072186},{"name":"Nicehash-X11","tag":"NICEHASH","algo":"X11","type":"asic","unit":"GH/s","mult":1000000000.0,"nethash":53452299654485.0,"reward":1.0,"blocktime":1.0,"price":2.7501891782},{"name":"Nicehash-Zhash","tag":"NICEHASH","algo":"Zhash","type":"gpu","unit":"MH/s","mult":1000000.0,"nethash":17048.0,"reward":1.0,"blocktime":1.0,"price":1245.0612124666},{"name":"OctaSpace","tag":"OCTA","algo":"Ethash","type":"gpu","unit":"MH/s","mult":1000000.0,"nethash":1436466163357.0,"reward":1.1,"blocktime":12.8908,"price":0.0882271873},{"name":"OctaSpace","tag":"OCTA","algo":"Ethash","type":"asic","unit":"MH/s","mult":1000000.0,"nethash":1436466163357.0,"reward":1.1,"blocktime":12.8908,"price":0.0882573042},{"name":"Pearl","tag":"PRL","algo":"Pearl","type":"gpu","unit":"MH/s","mult":1000000.0,"nethash":2.47387092137907e+19,"reward":2646.0984150368495,"blocktime":159.0,"price":0.749636235},{"name":"Peercoin","tag":"PPC","algo":"SHA-256","type":"asic","unit":"TH/s","mult":1000000000000.0,"nethash":8459162505829196.0,"reward":37.027445435460606,"blocktime":2700.0,"price":0.2273672931},{"name":"Phoenixcoin","tag":"PXC","algo":"NeoScrypt","type":"gpu","unit":"MH/s","mult":1000000.0,"nethash":1036677846.0,"reward":3.125,"blocktime":81.0,"price":0.0246780249},{"name":"Pirate","tag":"ARRR","algo":"Equihash","type":"asic","unit":"Sol/s","mult":1,"nethash":4136629.0,"reward":0.25,"blocktime":59.0,"price":0.3252792085},{"name":"Quai-KawPow","tag":"QUAI","algo":"KawPow","type":"gpu","unit":"MH/s","mult":1000000.0,"nethash":373149461668.0,"reward":6.235504102479167,"blocktime":1.772,"price":0.0190207701},{"name":"Quai-Scrypt","tag":"QUAI","algo":"Scrypt","type":"asic","unit":"GH/s","mult":1000000000.0,"nethash":9598433753833.0,"reward":6.1582842153802035,"blocktime":1.793,"price":0.0191672428},{"name":"Quai-SHA","tag":"QUAI","algo":"SHA-256","type":"asic","unit":"TH/s","mult":1000000000000.0,"nethash":2.1211783442457942e+17,"reward":6.1582842153802035,"blocktime":1.351,"price":0.0191672428},{"name":"Quantum R L","tag":"QRL","algo":"RandomX","type":"asic","unit":"kH/s","mult":1000.0,"nethash":81464993.0,"reward":1.325729106,"blocktime":60.0,"price":1.0139741394},{"name":"QuarkChain","tag":"QKC","algo":"Ethash","type":"gpu","unit":"MH/s","mult":1000000.0,"nethash":55450985308.0,"reward":1.32819568820224,"blocktime":9.8514,"price":0.0024877928},{"name":"QuarkChain","tag":"QKC","algo":"Ethash","type":"asic","unit":"MH/s","mult":1000000.0,"nethash":55450985308.0,"reward":1.32819568820224,"blocktime":9.8514,"price":0.0024926414},{"name":"Qubitcoin","tag":"QTC","algo":"Qhash","type":"gpu","unit":"MH/s","mult":1000000.0,"nethash":14513694775878.0,"reward":50.0,"blocktime":601.0,"price":0.7796216844},{"name":"Radiant","tag":"RXD","algo":"SHA512256d","type":"asic","unit":"MH/s","mult":1000000.0,"nethash":482563103105817.0,"reward":12500.0,"blocktime":299.0,"price":8.19882e-05},{"name":"Ravencoin","tag":"RVN","algo":"KawPow","type":"gpu","unit":"MH/s","mult":1000000.0,"nethash":1956640445704.0,"reward":1250.0,"blocktime":60.0,"price":0.004434848},{"name":"Ryo","tag":"RYO","algo":"CryptoNightGPU","type":"gpu","unit":"MH/s","mult":1000000.0,"nethash":512495.0,"reward":31.01,"blocktime":251.0,"price":0.0037966277},{"name":"ScPrime","tag":"SCP","algo":"Sia","type":"asic","unit":"MH/s","mult":1000000.0,"nethash":4270624727554673.0,"reward":45.00237375,"blocktime":569.0,"price":0.0231436708},{"name":"Tari-Cuckaroo29","tag":"XTM","algo":"Cuckaroo29","type":"gpu","unit":"MH/s","mult":1000000.0,"nethash":38615.0,"reward":10922.95615,"blocktime":363.2,"price":0.0006616789},{"name":"Tari-Merged","tag":"XTM","algo":"MoneroRandomX","type":"asic","unit":"MH/s","mult":1000000.0,"nethash":3804772490.0,"reward":10922.95615,"blocktime":778.2857,"price":0.0006619048},{"name":"Tari-RandomX","tag":"XTM","algo":"TariRandomX","type":"asic","unit":"MH/s","mult":1000000.0,"nethash":56634720.0,"reward":10922.95615,"blocktime":2724.0,"price":0.0006619048},{"name":"Tari-SHA3x","tag":"XTM","algo":"SHA3x","type":"gpu","unit":"MH/s","mult":1000000.0,"nethash":660752839971837.0,"reward":10922.95615,"blocktime":340.5,"price":0.0006616789},{"name":"Vertcoin","tag":"VTC","algo":"Verthash","type":"gpu","unit":"MH/s","mult":1000000.0,"nethash":994804379.0,"reward":6.25,"blocktime":156.0,"price":0.044909157},{"name":"Xelis","tag":"XEL","algo":"Xelishashv3","type":"gpu","unit":"MH/s","mult":1000000.0,"nethash":84985473.0,"reward":0.32703892,"blocktime":5.1515,"price":0.3098496438},{"name":"Zano","tag":"ZANO","algo":"ProgPowZ","type":"gpu","unit":"MH/s","mult":1000000.0,"nethash":546125283407.0,"reward":1.0,"blocktime":120.0,"price":8.357944263},{"name":"Zcash","tag":"ZEC","algo":"Equihash","type":"asic","unit":"Sol/s","mult":1,"nethash":18741535736.0,"reward":1.25,"blocktime":75.0,"price":335.6017455808},{"name":"Zephyr","tag":"ZEPH","algo":"RandomX","type":"asic","unit":"kH/s","mult":1000.0,"nethash":44645088.0,"reward":4.299949301515,"blocktime":119.0,"price":0.2708610365}]}